Workbook

Sheet START HERE
A1: HOURS + MILEAGE TRACKER — Rental Tax Strategies
A2: For Jason & Brandy Morgan • Built to prove hours, capture every deductible mile, and keep the profit-to-zero / equity / borrow-against-it stack audit-ready. Yellow cells are the only cells you type in.
A4: HOW TO USE THIS FILE (5 minutes to set up)
A5: 1. SETUP & INPUTS | B5: Fill every yellow cell once: names, tax year, other-job hours, home size, property list. Everything else pulls from there.
A6: 2. HOURS LOG | B6: Log time the same day you do it. Pick the Category honestly — 'Counts' vs 'Investor-type' is what wins or loses an audit. One row per work session.
A7: 3. HOURS TESTS | B7: No typing. This sheet grades Brandy's Real Estate Professional tests (750 hrs + more-than-half) and material-participation (500 hrs / 100-hr) automatically.
A8: 4. MILEAGE LOG | B8: You already use MileIQ — export it monthly and paste Date / Purpose / Miles here, or type trips in. Business miles only in the Business column; commuting goes in Personal.
A9: 5. HOME OFFICE & VEHICLE CALC | B9: Compares Simplified vs Actual home office, and Standard Mileage vs Actual vehicle, side by side. Pick one method per item per year and stay consistent.
A10: 6. KIDS & AUGUSTA | B10: Tracks each child's wages against their standard deduction, and counts Augusta Rule days so you never cross 14.
A11: 7. STRATEGY RULES | B11: The full rules list for all 7 strategies + the mortgage-interest myth. Read the 'Evidence to keep' column — that is your audit file.
A12: 8. YEAR-END PACKET | B12: Your hand-off checklist for your CPA / tax strategist. Totals flow in automatically; check off the documents as you gather them.
A14: LEGEND | B14: Yellow fill + blue text = you type here • White/grey = formula, do not overwrite • PASS / NEED = live grade from your logs
A15: THE STACK THIS SERVES | B15: 1) Drive reported rental profit toward $0 on paper (depreciation, expenses, losses that are actually usable) 2) Build real equity 3) Borrow against the property when you need cash — loan proceeds are not taxable income, and renters retire the note. Every strategy in this file is graded against that stack.
A16: IMPORTANT | B16: Educational tracker only — not tax advice. Tax law changes and your facts control. Confirm elections, grouping, and entity questions with your tax strategist BEFORE year-end; most of these strategies cannot be fixed in April.
A17: RATES BAKED IN (edit on SETUP) | B17: Standard mileage: $0.725/mile for 2026 (IRS Notice 2026-10); $0.70 for 2025. Home office simplified: $5/sq ft, max 300 sq ft = $1,500. Child standard deduction input defaults to $15,750 (2025) — update it yearly on the Kids sheet.

Sheet SETUP & INPUTS
A1: SETUP & INPUTS — fill the yellow cells once
A2: Every other sheet reads from here. If a name or property is spelled differently in a log, the totals will miss it — copy these spellings exactly (or use the dropdowns).
A4: Item | B4: Your entry (yellow) | C4: Notes — read before you type
A5: Tax year | B5: 2026 | C5: Change this and check the mileage rate + standard deduction for that year.
A6: Real-estate pro (spouse) | B6: Brandy Morgan | C6: The person taking the 750-hr / more-than-half tests. On a joint return, one spouse qualifying unlocks the family's rental losses.
A7: Other spouse / partner | B7: Jason Morgan
A8: Brandy — hours in ALL other jobs/businesses this year | B8: 0 | C8: Needed for the more-than-half test. Example: 1,000 hrs at an outside job means she needs MORE than 1,000 real-estate hours. Leave 0 if real estate is her only work.
A9: Jason — hours in ALL other jobs/businesses this year | B9: 0 | C9: Same test, for Jason if he ever takes it.
A10: IRS standard mileage rate ($/mile) | B10: 0.725 | C10: 2026: $0.725 (Notice 2026-10). 2025: $0.70. Update when IRS announces a new rate.
A11: Home — total living area (sq ft) | B11: 2000 | C11: For home-office %. Measure once; keep a sketch/photo in your tax file.
A12: Home office — exclusive business area (sq ft) | B12: 150 | C12: Must be used exclusively + regularly for the business to qualify. Simplified method caps at 300 sq ft.
A13: Grouping election made? (Yes/No) | B13: No | C13: Electing to treat all rental properties as ONE activity can make material participation reachable. Must be a formal election — ask your strategist before filing.
A14: Business entity type | B14: Sole prop / single-member LLC | C14: Matters for hiring kids (FICA exemption) and Augusta Rule (needs a separate entity). Options in next column notes.
A16: YOUR PROPERTIES — type the exact names you will use in the logs
A17: Property name (yellow) | B17: Type (Long-term / Short-term / House-hack unit) | C17: Notes
A18: 308 Paula | B18: Long-term
A19: 4800 Kent Ave, Groves TX | B19: Long-term
A20: Property 3
A21: Property 4
A22: Property 5
A23: Property 6
A25: Activity categories for the Hours Log (do not rename — formulas look for these words):
A26: Counts - operational | B26: Day-to-day running of the rental: tenant calls, showings, leasing, repairs coordination, cleaning oversight, bookkeeping for operations, travel to the property. COUNTS toward REPS + material participation.
A27: Investor-type | B27: Reviewing statements, reading market reports, studying new deals, talking to your CPA about planning. Real work, but the IRS does NOT count investor-type hours toward material participation unless you are directly involved in day-to-day operations. Log it, but do not rely on it.
A28: Personal - does not count | B28: Personal time at a house-hack home, commuting, family time. Never counts. Logging it honestly protects the credibility of the whole log.

Sheet HOURS LOG
A1: HOURS LOG — log it the same day
A2: One row per work session. Contemporaneous logs win audits; rebuilt-at-tax-time logs lose them. Keep texts, calendars and invoices that back up each row.
A4: Date | B4: Person | C4: Property / Unit | D4: What you did (be specific) | E4: Category | F4: Hours | G4: Evidence (calendar / text / invoice / photo) | H4: Month
A5: 2026-01-05 | B5: Brandy Morgan | C5: 308 Paula | D5: Called plumber, met him at unit, approved repair quote, paid invoice | E5: Counts - operational | F5: 2.5 | G5: Calendar invite + plumber invoice #___ | H5: =IF(A5="","",TEXT(A5,"YYYY-MM")) -> 2026-01
A6: 2026-01-06 | B6: Brandy Morgan | C6: 308 Paula | D6: Reviewed monthly bank statement and rent roll | E6: Investor-type | F6: 0.75 | G6: Bank statement (investor-type — does not count toward participation) | H6: =IF(A6="","",TEXT(A6,"YYYY-MM")) -> 2026-01
A7: 2026-01-07 | B7: Brandy Morgan | C7: 4800 Kent Ave, Groves TX | D7: Showed unit to 2 applicants, ran applications, called references | E7: Counts - operational | F7: 3 | G7: Showing calendar + application emails | H7: =IF(A7="","",TEXT(A7,"YYYY-MM")) -> 2026-01
H8: =IF(A8="","",TEXT(A8,"YYYY-MM"))
H9: =IF(A9="","",TEXT(A9,"YYYY-MM"))
H10: =IF(A10="","",TEXT(A10,"YYYY-MM"))
H11: =IF(A11="","",TEXT(A11,"YYYY-MM"))
H12: =IF(A12="","",TEXT(A12,"YYYY-MM"))
H13: =IF(A13="","",TEXT(A13,"YYYY-MM"))
H14: =IF(A14="","",TEXT(A14,"YYYY-MM"))
H15: =IF(A15="","",TEXT(A15,"YYYY-MM"))
H16: =IF(A16="","",TEXT(A16,"YYYY-MM"))
H17: =IF(A17="","",TEXT(A17,"YYYY-MM"))
H18: =IF(A18="","",TEXT(A18,"YYYY-MM"))
H19: =IF(A19="","",TEXT(A19,"YYYY-MM"))
... H207: =IF(A207="","",TEXT(A207,"YYYY-MM"))
A208: TOTALS (all rows above) | F208: =SUM(F5:F207) -> 6.25

Sheet HOURS TESTS
A1: HOURS TESTS — your live grade (no typing here, except the two yellow boxes)
A2: These grades read straight from the Hours Log + Setup. A 'NEED' in October is fixable; the same 'NEED' discovered in April is not. Check monthly.
A4: REAL ESTATE PROFESSIONAL STATUS (REPS) — the person named on Setup row 6 (Brandy)
A5: Brandy — 'Counts - operational' hours (from log) | B5: =SUMIFS('HOURS LOG'!F:F,'HOURS LOG'!B:B,'SETUP & INPUTS'!B6,'HOURS LOG'!E:E,"Counts - operational") -> 5.5 | C5: These are the only hours the IRS counts here. Investor-type hours are excluded on purpose.
A6: Brandy — Investor-type hours (logged, NOT counted) | B6: =SUMIFS('HOURS LOG'!F:F,'HOURS LOG'!B:B,'SETUP & INPUTS'!B6,'HOURS LOG'!E:E,"Investor-type") -> 0.75 | C6: If this is bigger than the row above, the log itself is the problem — rebalance toward hands-on work.
A7: TEST 1 — More than 750 hours? | B7: =IF(B5>750,"PASS","NEED "&TEXT(750-B5,"0")&" more hrs") -> NEED 745 more hrs | C7: IRS Sec. 469(c)(7): must perform MORE than 750 hours in real-property trades/businesses you materially participate in.
A8: TEST 2 — More than half of ALL your working time? | B8: =IF((B5/(B5+'SETUP & INPUTS'!B8))>0.5,"PASS — "&TEXT(B5/(B5+'SETUP & INPUTS'!B8),"0%")&" in real estate","NEED — only "&TEXT(IF((B5+'SETUP & INPUTS'!B8)=0,0,B5/(B5+'SETUP & INPUTS'!B8)),"0%")&" in real estate") -> PASS — 100% in real estate | C8: More than half of personal services in ALL trades/businesses must be real-property work. Outside-job hours come from Setup.
A9: REPS overall | B9: =IF(AND(B7="PASS",LEFT(B8,4)="PASS"),"PASS — REPS met (still need material participation per property/group below)","NOT YET") -> NOT YET | C9: BOTH tests must pass in the same year, for the same person. On a joint return, one spouse passing unlocks the family's rental losses.
A11: MATERIAL PARTICIPATION — per property (REPS alone is not enough; you must also materially participate in the rental activity)
A12: Property (from Setup) | B12: Brandy 'Counts' hrs | C12: 500-hr test | D12: Most hours by ANY other person (cleaner/manager) — type it | E12: 100-hr test (>100 & more than anyone else) | F12: Property verdict
A13: ='SETUP & INPUTS'!A18 -> 308 Paula | B13: =SUMIFS('HOURS LOG'!F:F,'HOURS LOG'!C:C,A13,'HOURS LOG'!B:B,'SETUP & INPUTS'!B6,'HOURS LOG'!E:E,"Counts - operational") -> 2.5 | C13: =IF(B13>500,"PASS","—") -> — | D13: 0 | E13: =IF(AND(B13>100,B13>D13),"PASS","—") -> — | F13: =IF(OR(C13="PASS",E13="PASS"),"MATERIALLY PARTICIPATES","Not yet") -> Not yet
A14: ='SETUP & INPUTS'!A19 -> 4800 Kent Ave, Groves TX | B14: =SUMIFS('HOURS LOG'!F:F,'HOURS LOG'!C:C,A14,'HOURS LOG'!B:B,'SETUP & INPUTS'!B6,'HOURS LOG'!E:E,"Counts - operational") -> 3 | C14: =IF(B14>500,"PASS","—") -> — | D14: 0 | E14: =IF(AND(B14>100,B14>D14),"PASS","—") -> — | F14: =IF(OR(C14="PASS",E14="PASS"),"MATERIALLY PARTICIPATES","Not yet") -> Not yet
A15: ='SETUP & INPUTS'!A20 -> Property 3 | B15: =SUMIFS('HOURS LOG'!F:F,'HOURS LOG'!C:C,A15,'HOURS LOG'!B:B,'SETUP & INPUTS'!B6,'HOURS LOG'!E:E,"Counts - operational") -> 0 | C15: =IF(B15>500,"PASS","—") -> — | D15: 0 | E15: =IF(AND(B15>100,B15>D15),"PASS","—") -> — | F15: =IF(OR(C15="PASS",E15="PASS"),"MATERIALLY PARTICIPATES","Not yet") -> Not yet
A16: ='SETUP & INPUTS'!A21 -> Property 4 | B16: =SUMIFS('HOURS LOG'!F:F,'HOURS LOG'!C:C,A16,'HOURS LOG'!B:B,'SETUP & INPUTS'!B6,'HOURS LOG'!E:E,"Counts - operational") -> 0 | C16: =IF(B16>500,"PASS","—") -> — | D16: 0 | E16: =IF(AND(B16>100,B16>D16),"PASS","—") -> — | F16: =IF(OR(C16="PASS",E16="PASS"),"MATERIALLY PARTICIPATES","Not yet") -> Not yet
A17: ='SETUP & INPUTS'!A22 -> Property 5 | B17: =SUMIFS('HOURS LOG'!F:F,'HOURS LOG'!C:C,A17,'HOURS LOG'!B:B,'SETUP & INPUTS'!B6,'HOURS LOG'!E:E,"Counts - operational") -> 0 | C17: =IF(B17>500,"PASS","—") -> — | D17: 0 | E17: =IF(AND(B17>100,B17>D17),"PASS","—") -> — | F17: =IF(OR(C17="PASS",E17="PASS"),"MATERIALLY PARTICIPATES","Not yet") -> Not yet
A18: ='SETUP & INPUTS'!A23 -> Property 6 | B18: =SUMIFS('HOURS LOG'!F:F,'HOURS LOG'!C:C,A18,'HOURS LOG'!B:B,'SETUP & INPUTS'!B6,'HOURS LOG'!E:E,"Counts - operational") -> 0 | C18: =IF(B18>500,"PASS","—") -> — | D18: 0 | E18: =IF(AND(B18>100,B18>D18),"PASS","—") -> — | F18: =IF(OR(C18="PASS",E18="PASS"),"MATERIALLY PARTICIPATES","Not yet") -> Not yet
A20: If the Grouping election on SETUP is 'Yes', judge material participation on the COMBINED hours across all properties instead of per-property. The election is formal (statement attached to the return) — do not assume it.
A21: THE OTHER MATERIAL-PARTICIPATION TESTS (any ONE is enough — IRS Pub. 925): 1) >500 hrs in the activity 2) You do substantially all the work 3) >100 hrs and no one else does more 4) Significant-participation activities total >500 hrs 5) You materially participated in 5 of the prior 10 years 6) Personal-service activity you participated in for 3 prior years 7) Facts-and-circumstances: regular, continuous, substantial involvement (>100 hrs, nobody else paid more). For SHORT-TERM rentals (7-day rule), use the same tests — but you do NOT need REPS at all; material participation alone makes STR losses non-passive.

Sheet MILEAGE LOG
A1: MILEAGE LOG — MileIQ does the counting, this sheet does the tax math
A2: Paste your MileIQ export monthly, or type trips in. IRS wants: date, destination, business purpose, miles. Commuting (home to your regular workplace) is never deductible — it goes in Personal.
A4: Date | B4: Driver | C4: Vehicle | D4: From | E4: To / Property | F4: Business purpose (specific) | G4: Business Miles | H4: Personal / Commute Miles | I4: Total Miles | J4: Source | K4: Month
A5: 2026-01-05 | B5: Brandy Morgan | C5: Truck | D5: Home office | E5: 308 Paula | F5: Meet plumber, approve repair | G5: 18.4 | H5: 0 | I5: =G5+H5 -> 18.4 | J5: MileIQ | K5: =IF(A5="","",TEXT(A5,"YYYY-MM")) -> 2026-01
A6: 2026-01-07 | B6: Brandy Morgan | C6: Truck | D6: Home office | E6: 4800 Kent Ave, Groves TX | F6: Show unit to applicants | G6: 22.1 | H6: 0 | I6: =G6+H6 -> 22.1 | J6: Manual | K6: =IF(A6="","",TEXT(A6,"YYYY-MM")) -> 2026-01
I7: =G7+H7 -> 0 | K7: =IF(A7="","",TEXT(A7,"YYYY-MM"))
I8: =G8+H8 -> 0 | K8: =IF(A8="","",TEXT(A8,"YYYY-MM"))
I9: =G9+H9 -> 0 | K9: =IF(A9="","",TEXT(A9,"YYYY-MM"))
I10: =G10+H10 -> 0 | K10: =IF(A10="","",TEXT(A10,"YYYY-MM"))
I11: =G11+H11 -> 0 | K11: =IF(A11="","",TEXT(A11,"YYYY-MM"))
I12: =G12+H12 -> 0 | K12: =IF(A12="","",TEXT(A12,"YYYY-MM"))
I13: =G13+H13 -> 0 | K13: =IF(A13="","",TEXT(A13,"YYYY-MM"))
I14: =G14+H14 -> 0 | K14: =IF(A14="","",TEXT(A14,"YYYY-MM"))
I15: =G15+H15 -> 0 | K15: =IF(A15="","",TEXT(A15,"YYYY-MM"))
I16: =G16+H16 -> 0 | K16: =IF(A16="","",TEXT(A16,"YYYY-MM"))
I17: =G17+H17 -> 0 | K17: =IF(A17="","",TEXT(A17,"YYYY-MM"))
I18: =G18+H18 -> 0 | K18: =IF(A18="","",TEXT(A18,"YYYY-MM"))
... I206: =G206+H206 -> 0 | K206: =IF(A206="","",TEXT(A206,"YYYY-MM"))
A207: TOTALS | G207: =SUM(G5:G206) -> 40.5 | H207: =SUM(H5:H206) -> 0 | I207: =SUM(I5:I206) -> 40.5

Sheet MILEAGE SUMMARY
A1: MILEAGE SUMMARY — what the deduction is actually worth (no typing)
A2: Standard mileage already includes gas, insurance, repairs and depreciation — you cannot deduct those again separately for the same miles. Parking and tolls for business trips may be added on top; keep receipts.
A4: Measure | B4: Amount | C4: How it is figured
A5: Total business miles (year) | B5: =SUM('MILEAGE LOG'!G5:G206) -> 40.5 | C5: Sum of Business Miles in the Mileage Log
A6: Total personal / commute miles (year) | B6: =SUM('MILEAGE LOG'!H5:H206) -> 0 | C6: Needed to prove business-use % for the Actual-Expense method
A7: Total miles (year) | B7: =B5+B6 -> 40.5 | C7: Cross-check against Jan 1 / Dec 31 odometer photos — take both, every year
A8: Business-use % | B8: =IF(B7=0,0,B5/B7) -> 1 | C8: Actual vehicle costs are deductible only at this %
A9: IRS rate used ($/mile) | B9: ='SETUP & INPUTS'!B10 -> 0.725 | C9: From SETUP. 2026: $0.725; 2025: $0.70
A10: STANDARD MILEAGE DEDUCTION | B10: =B5*B9 -> 29.3625 | C10: Business miles x rate. This is most small landlords' best answer — no receipts for gas/repairs needed, but the mileage log itself is mandatory
A11: Business miles — Brandy | B11: =SUMIFS('MILEAGE LOG'!G:G,'MILEAGE LOG'!B:B,'SETUP & INPUTS'!B6) -> 40.5 | C11: By driver, from the log
A12: Business miles — Jason | B12: =SUMIFS('MILEAGE LOG'!G:G,'MILEAGE LOG'!B:B,'SETUP & INPUTS'!B7) -> 0 | C12: By driver, from the log
A14: MILEAGE TIPS THAT MOVE THE NUMBER: 1) The drive from home counts when your home office is your principal place of business — another reason the home-office setup matters. Without it, the first trip of the day risks being a non-deductible commute. 2) Bank, supply-store, CPA and courthouse runs for the rental business count — log the purpose specifically. 3) One odometer photo on Jan 1 and one on Dec 31 proves total miles; business % collapses without it. 4) MileIQ classifies drives — swipe within the week; a year of unclassified drives at tax time reads as reconstruction. 5) Never deduct the same cost twice: standard mileage OR actual expenses per vehicle per year (see Home Office & Vehicle sheet). 6) Trips to look at a property you did not buy can still be business travel if you are already in the rental business — write down what you evaluated and why you passed.

Sheet HOME OFFICE & VEHICLE
A1: HOME OFFICE & VEHICLE CALCULATOR — pick one method each, then stay consistent
A2: Yellow = your bills for the year. The sheet does both methods so you can see which wins before you commit on the return.
A4: HOME OFFICE — the space must be used EXCLUSIVELY and REGULARLY as the principal place of the rental business (IRS Pub. 587)
A5: Home (sq ft) | B5: ='SETUP & INPUTS'!B11 -> 2000 | C5: Simplified: $5/sq ft up to 300 sq ft = $1,500 max. No expense records, no depreciation, no recapture on that space later. Actual (below) usually wins when the office % x total house bills exceeds $1,500. You may switch methods year to year — the election is annual.
A6: Office (sq ft) — exclusive | B6: ='SETUP & INPUTS'!B12 -> 150
A7: Business % of home | B7: =IF(B5=0,0,B6/B5) -> 0.075
A8: SIMPLIFIED deduction | B8: =MIN(B6,300)*5 -> 750
A10: ACTUAL method — annual cost of running the home (yellow) | B10: Annual $ | C10: Business share
A11: Mortgage interest (not principal) | B11: 0 | C11: =$B$7*B11 -> 0
A12: Real-estate taxes | B12: 0 | C12: =$B$7*B12 -> 0
A13: Homeowners insurance | B13: 0 | C13: =$B$7*B13 -> 0
A14: Electric / gas / water / trash | B14: 0 | C14: =$B$7*B14 -> 0
A15: Internet | B15: 0 | C15: =$B$7*B15 -> 0
A16: Repairs & maintenance (whole home) | B16: 0 | C16: =$B$7*B16 -> 0
A17: Cleaning | B17: 0 | C17: =$B$7*B17 -> 0
A18: Other (describe in notes) | B18: 0 | C18: =$B$7*B18 -> 0
A19: Direct office-only expenses (100% deductible, e.g. office paint, dedicated line) | B19: 0 | C19: =B19 -> 0
A20: ACTUAL home-office deduction (before depreciation) | B20: =SUM(C11:C19) -> 0
A21: Home-office traps: 1) A spare bedroom that doubles as a guest room fails the exclusive-use test. 2) Actual method may add depreciation on the office % of the home's basis — that slice can be recaptured when you sell; simplified avoids it. 3) Home-office status is what can turn the drive from home to a rental into deductible business travel instead of a commute. 4) W-2 employees cannot claim this deduction (suspended 2018-2025 and generally unavailable to employees); it is for the self-employed / business side — rentals reported as a business should confirm treatment with the strategist.
A25: VEHICLE — Standard Mileage vs Actual Expenses (choose ONE per vehicle, per year)
A26: Standard mileage deduction (from Mileage Summary) | B26: ='MILEAGE SUMMARY'!B10 -> 29.3625 | C26: Vehicle rules of thumb: Standard is best for paid-off, fuel-efficient vehicles driven a lot for business. Actual can win for expensive trucks with high running costs — but it demands every receipt and still only counts at the business %. Switching rules: if you used Actual with accelerated depreciation on a vehicle, you may be locked out of Standard for it later — decide in year one with the strategist. Keep Jan 1 / Dec 31 odometer photos either way.
A27: Business-use % (from Mileage Summary) | B27: ='MILEAGE SUMMARY'!B8 -> 1
A28: ACTUAL — annual vehicle costs (yellow) | B28: $ / year
A29: Gas / charging | B29: 0
A30: Insurance | B30: 0
A31: Repairs & tires | B31: 0
A32: Registration / taxes | B32: 0
A33: Loan interest (business share handled by %) | B33: 0
A34: Lease payments | B34: 0
A35: Other vehicle costs | B35: 0
A36: ACTUAL vehicle deduction (costs x business %) | B36: =SUM(B29:B35)*B27 -> 0
A37: HIGHER of the two (guide only — method rules control) | B37: =MAX(B26,B36) -> 29.3625
A39: A PORTION OF EVERYDAY BILLS IS THE POINT: at a 15% office share, 15% of electric, internet, insurance and whole-home repairs becomes a business deduction; at a 40% business-driving share, 40% of vehicle costs does. Small percentages on big household bills are real money across a year — but only with the logs to prove the percentages.

Sheet KIDS & AUGUSTA
A1: HIRE YOUR KIDS + AUGUSTA RULE TRACKERS
A2: Kids: real jobs, reasonable pay, payroll paperwork — the deduction survives on documentation. Augusta: 14 days is a hard wall, not an average.
A4: HIRE YOUR KIDS — wages you deduct, they shelter under their own standard deduction
A5: Standard deduction per child ($) — update yearly | B5: 15750 | C5: Default shown is the 2025 figure ($15,750) — replace it with the current year's amount. A child can earn up to this in W-2 wages and owe $0 federal income tax; earned wages also unlock a custodial Roth IRA (up to their earned income, within the annual IRA limit).
A7: Child name | B7: Age | C7: Job duties (real + age-appropriate) | D7: Hours/yr | E7: Pay $/hr | F7: Wages (formula) | G7: Deduction room left | H7: FICA note
A8: Example — delete me | B8: 14 | C8: Yard work, unit clean-up, photos for listings | D8: 120 | E8: 15 | F8: =D8*E8 -> 1800 | G8: =$B$5-F8 -> 13950 | H8: =IF(B8="","",IF(B8<18,"Under 18: FICA-exempt IF sole prop / parents-only partnership","18+: payroll taxes apply")) -> Under 18: FICA-exempt IF sole prop / parents-only partnership
A9: Child 2 | D9: 0 | E9: 0 | F9: =D9*E9 -> 0 | G9: =$B$5-F9 -> 15750 | H9: =IF(B9="","",IF(B9<18,"Under 18: FICA-exempt IF sole prop / parents-only partnership","18+: payroll taxes apply"))
A10: Child 3 | D10: 0 | E10: 0 | F10: =D10*E10 -> 0 | G10: =$B$5-F10 -> 15750 | H10: =IF(B10="","",IF(B10<18,"Under 18: FICA-exempt IF sole prop / parents-only partnership","18+: payroll taxes apply"))
A11: Child 4 | D11: 0 | E11: 0 | F11: =D11*E11 -> 0 | G11: =$B$5-F11 -> 15750 | H11: =IF(B11="","",IF(B11<18,"Under 18: FICA-exempt IF sole prop / parents-only partnership","18+: payroll taxes apply"))
A12: Total wages deducted by the business | F12: =SUM(F8:F11) -> 1800
A13: ALL THE RULES — HIRING YOUR KIDS: 1) Work must be legitimate and age-appropriate; pay must be reasonable for the job (what you'd pay a stranger). 2) Under 18 working for a sole proprietorship or a partnership where each partner is a parent: wages are exempt from Social Security/Medicare (FICA); under 21 also exempt from federal unemployment (FUTA). Corporations (incl. S-corps) do NOT get this exemption on the owner's children. 3) Issue a W-2 (they are employees, not 1099 contractors), run real payroll, pay by check/transfer into an account in the child's name — never cash, never round-number 'allowances'. 4) Keep timesheets (the Hours Log works — put the child as Person), a written job description, and proof of payment. 5) State child-labor law still controls hours/jobs. 6) Wages are earned income, so the kiddie tax does not apply to them. 7) The business deducts the wages as an ordinary business expense (IRC Sec. 162); the child shelters up to their standard deduction.
A18: AUGUSTA RULE (IRC Sec. 280A(g)) — rent your home to your own business up to 14 days a year, tax-free to you, deductible to the business
A19: Fair-market rent per day ($) — document comps | B19: 500 | C19: Needs a REAL separate business entity — a sole proprietor cannot rent a home to themselves. Business must actually use the home (meetings, planning days, content/records days), pay fair-market rent (save 2-3 hotel/meeting-space comps), write minutes/invoices, and pay by check. Day 15 destroys the exclusion for ALL the days — watch the counter.
A20: Days used so far | B20: =COUNTA(A24:A37) -> 0
A21: Days remaining (of 14) | B21: =14-B20 -> 14
A22: Tax-free income so far | B22: =B20*B19 -> 0
A23: Date | B23: Business purpose | C23: Who attended | D23: Rent charged | E23: Paid? (check #)

Sheet STRATEGY RULES
A1: STRATEGY RULES — the full rules list for all 7 (+ the myth that is not a strategy)
A2: Ordered for a working landlord whose goal is: paper profit toward $0, real equity up, cash out by borrowing against the property (not taxable), renters retire the note. 'Plan ahead?' is the column that decides what you do BEFORE December.
A4: Strategy | B4: What it does for you | C4: ALL the rules (complete list) | D4: Numbers to know | E4: Plan ahead? | F4: Evidence to keep | G4: How it most often fails / watch-outs
A5: 0 — THE MYTH: 'Keep a mortgage for the interest write-off' | B5: Nothing. It is a bank story. $10,000 of interest at a 24% bracket saves $2,400 of tax — you spent $10,000 to save $2,400 and are $7,600 poorer for the privilege. | C5: 1) Interest is only deductible as a business cost — it is never a benefit by itself. 2) Paying tax on profit means you MADE profit; paying interest to avoid it trades $1.00 for ~$0.24-$0.37. 3) Strategy is the opposite: zero the paper profit with depreciation + real expenses, build equity, borrow against equity when cash is needed (loan proceeds are not income). | D5: Example: $10,000 interest x 24% = $2,400 tax saved; net cost $7,600. | E5: No | F5: A one-line note in your plan so nobody 'optimizes' you back into debt for deductions. | G5: Letting a lender or tax preparer frame debt as a tax strategy. CPA processes; a tax strategist plans — this is the difference.
A6: 1 — Short-Term Rental (STR) exception | B6: Rent by the week and run it yourself: rental losses (powered by cost segregation) can offset job/business income WITHOUT being a real-estate professional. | C6: 1) Average guest stay must be 7 days or less (total rented days / bookings), OR 30 days or less WITH substantial services (during-stay cleaning, meals, concierge-type services). 2) You must MATERIALLY PARTICIPATE (any one Pub. 925 test: >500 hrs; >100 hrs and more than anyone else incl. cleaners/managers; you do substantially all the work; etc.). 3) Then the activity is treated as a business, not a rental — Sec. 469 passive limits do not shelve the losses. 4) If a property manager does more than you, you fail — structure duties accordingly. 5) Personal use > greater of 14 days or 10% of rented days converts it toward a residence with loss limits. 6) Excess-business-loss limits can cap very large losses in a year; the rest carries forward. | D6: 7-day average is the whole ballgame. Example pattern: $250k paper loss from a cost-seg study offsetting salary can be worth $50k+ of tax in that year (illustration, not a promise). | E6: YES — setup before first guests | F6: Hours Log (you vs everyone else!), booking reports proving average stay, listing/calendar exports, cleaner/manager invoices showing fewer hours than yours. | G6: Hiring a full-service manager (their hours exceed yours), letting average stays drift over 7 days with monthly renters, reconstructed hour logs.
A7: 2 — Real Estate Professional Status (REPS) + grouping | B7: For long-term rentals: one spouse qualifies, the whole family's rental losses become usable against other income. This is Brandy's lane. | C7: 1) SAME person must pass BOTH: (a) MORE than 750 hours in real-property trades/businesses in which they materially participate, and (b) MORE than half of ALL their working time that year is in those businesses (Sec. 469(c)(7)). 2) Spouses cannot pool hours for the 750/>50% tests (joint return: either spouse may qualify, individually). 3) REPS alone is not enough — you must ALSO materially participate in the rental activity (per property, OR elect to group all rentals as one activity). 4) Real-property businesses include rental operation, management, leasing, construction, acquisition, development, brokerage. 5) Employee hours in someone else's real-estate business count only if you own >5%. 6) Investor-type hours (reviewing statements, studying deals) do not count toward material participation. 7) No formal election files REPS itself, but the GROUPING election is formal, on the return, and generally binding. | D7: 750 hrs ≈ 14.5 hrs/week every week. >50%: a 1,000-hr outside job needs >1,000 real-estate hrs. Losses then offset the other spouse's income on a joint return. | E7: YES — hours happen all year or not at all | F7: Contemporaneous Hours Log (operational category), calendars, tenant/repair communications, outside-job hour proof for the >50% denominator. | G7: Counting investor-type hours, an outside W-2 quietly breaking the >50% test, no log (Tax Court routinely denies REPS without credible time records).
A8: 3 — Cost segregation + bonus depreciation (the engine) | B8: Carves 20-35% of a building's price out of 27.5-year depreciation into 5/7/15-year parts, then writes those parts off immediately with bonus depreciation. Creates the paper loss that Strategies 1 & 2 make usable. | C8: 1) Needs an engineering-based study (or defensible DIY/software study for small properties) allocating price among land (never depreciable), building (27.5-yr residential / 39-yr commercial), personal property (5/7-yr) and land improvements (15-yr). 2) Bonus applies only to components with recovery of 20 years or less — the study is what creates eligible components. 3) Current law: 100% bonus for qualifying property acquired and placed in service after Jan 19, 2025 (restored permanently by the 2025 Act, replacing the phase-down) — confirm the rate for your placed-in-service year with the strategist. 4) Property must be placed in service (ready and available to rent) in the year claimed. 5) A big paper loss only HELPS if it is usable (Strategy 1, 2, or passive income to absorb it) — otherwise it suspends. 6) Depreciation lowers basis; on a later taxable sale, unrecaptured Sec. 1250 gain is taxed up to 25%, personal-property recapture at ordinary rates. | D8: Typical reclass: 20-35% of building price. On a $500k property, year-one depreciation can jump from ~$14.5k (straight 27.5-yr) to ~$130k with study + 100% bonus (illustration). | E8: YES — order the study in the purchase year | F8: The study report itself, closing statement, placed-in-service proof (listing/lease), photos of components. | G8: Doing the study when losses cannot be used, forgetting recapture in exit math: heavy write-offs + heavy borrowing + taxable sale can leave tax bigger than cash left — pair with Strategy 4/5 exits.
A9: 4 — 1031 exchange (the exit door) | B9: Sell an investment property and roll ALL proceeds into the next investment property: capital-gain tax AND depreciation recapture deferred (not forgiven). Keeps the equity compounding. | C9: 1) Both properties must be US real property held for business/investment — no personal residences, no fix-and-flip inventory. 2) A Qualified Intermediary (QI) must hold the sale money; you can never touch or control the proceeds (no constructive receipt). 3) Identify replacement(s) IN WRITING to the QI within 45 days of sale (3-property rule, or 200%/95% alternatives). 4) Close within 180 days of sale OR the tax-return due date for that year, whichever is earlier (file an extension if needed). 5) Same taxpayer must take title. 6) For FULL deferral: buy equal-or-greater value and replace equal-or-greater debt; any cash/non-like-kind kept ('boot') is taxable. 7) Related-party exchanges carry a 2-year hold rule. 8) File Form 8824. Deadlines are calendar days with no extensions for weekends in most cases — treat them as immovable. | D9: 45 / 180 days, both clocks start at sale closing. Deferral can chain for decades; basis steps up at death under current law, which can erase the deferred gain entirely. | E9: YES — QI engaged BEFORE the sale closes | F9: QI agreement, written 45-day identification, settlement statements, Form 8824. Never let proceeds hit your account, even overnight. | G9: Missing day 45 by one day = full tax. Touching the money = full tax. Buying less house = partial tax on the shortfall (boot).
A10: 5 — Sell-your-home exclusion stacked with a 1031 (house-hack exit) | B10: The only play that makes gain DISAPPEAR (not defer): live in one unit of a 2-4 unit property, rent the rest; at sale your unit's gain is excluded tax-free, the rental side rolls onward in a 1031. Matches the live-in-one, rent-three setup. | C10: 1) Exclusion (Sec. 121): up to $250,000 single / $500,000 married filing jointly of gain excluded if you OWNED and USED the home as your main home for 2 of the 5 years before sale. 2) Generally once every 2 years. 3) A multi-unit property is two assets at sale: your residence portion gets the exclusion; the rental portion does not — allocate price, basis and depreciation by a reasonable method (units or square footage; duplex defaults matter — document yours). 4) Depreciation taken on the rental portion after May 6, 1997 is NOT excludable — it is recaptured (up to 25%) even on the residence side's unrecaptured portion. 5) The rental portion can go into a 1031 (needs its own QI/deadlines — Strategy 4). 6) Periods of nonqualified use after 2008 can prorate away part of the exclusion — long rentals before moving in matter. | D10: Worked pattern (from your 4-plex example): $600k buy, sell $800k in 5 yrs — your unit's ~$40k gain excluded to $0; rental side ~$185k splits into ~$65k recapture (to 25%) + ~$120k capital gain — that rental side is what the 1031 must carry. | E10: YES — allocation method chosen at purchase, not at sale | F10: Settlement split, square-footage/unit allocation worksheet, depreciation schedules per portion, occupancy proof (mail, license, utilities). | G10: Waiting until closing week to allocate, forgetting depreciation recapture survives the exclusion, missing the 2-of-5-years use test after moving out (3-year window to sell).
A11: 6 — Hire your kids | B11: Pay your children real wages for real work: the business deducts it, the child shelters it under their own standard deduction, and the wages unlock a custodial Roth IRA. Roughly $15k+ per child per year moves from your bracket to 0%. | C11: 1) Legitimate, age-appropriate work at reasonable pay (see Kids & Augusta sheet for the payroll/FICA/W-2 rule list — all of it applies). 2) Amount up to the child's standard deduction owes $0 federal income tax; above it, taxed at the CHILD's low rates. 3) Earned wages are not hit by the kiddie tax. 4) Under-18 FICA exemption only through a sole prop / parents-only partnership (an S-corp must route carefully or pay payroll tax). 5) Deductible to the business under Sec. 162 as ordinary-and-necessary wages. 6) Child-labor law (state) still governs. | D11: Per child: up to the standard deduction tax-free (default input $15,750 for 2025 on the Kids sheet — update yearly). Two kids at the cap ≈ $31k+ of deductions moved off your return. | E11: SOME — payroll must exist before wages are paid | F11: Timesheets/job description, payroll register, W-2, bank proof into the child's own account, Roth statements. | G11: Paying a 7-year-old an executive salary, no timesheets, cash 'pay'. Reasonable for the work means reasonable for a stranger doing the same job.
A12: 7 — Augusta Rule (Sec. 280A(g)) | B12: Rent your own home to your own business for up to 14 days a year: the business deducts fair-market rent; you personally exclude it from income entirely. Small dollars, almost free to run once documented. | C12: 1) Rent the residence 14 days or FEWER in the year — day 15 makes ALL days taxable. 2) Rent must be fair market (document hotel/meeting-space comps). 3) There must be a real business that actually uses the home (board meetings, planning, records, production days) with minutes/agendas. 4) Needs a SEPARATE business entity — a sole proprietor cannot rent to themselves. 5) Business pays by check/transfer and deducts it as rent expense; homeowner excludes under Sec. 280A(g) (no expense deductions against excluded rent beyond normal mortgage interest/taxes on Schedule A). 6) State treatment varies — confirm. | D12: Example: 14 days x $500 fair rent = $7,000 tax-free to you, $7,000 deducted by the business. Tracked on the Kids & Augusta sheet so day 15 never happens by accident. | E12: SOME — entity + first meeting documented before first rental | F12: Written rental agreement, comparable pricing printouts, meeting minutes, invoice + proof of business payment, day counter (Kids & Augusta sheet). | G12: No separate entity, no documentation of actual business use, drifting to day 15, pricing rent at whatever you wish the deduction was.
A13: BONUS — House-hack numbers (live in 1, rent 3) | B13: Your personal setup, scored with the same 7 strategies: your building is treated as TWO properties (your home + rentals) for expenses, depreciation and sale — while Strategies 2/6/7 run on top of it. | C13: 1) Expenses split by a reasonable method (units or square footage) between personal and rental portions. 2) Depreciation only on the rental portion, and only on the BUILDING share (land excluded): e.g. $600k 4-plex, 75% rented, building portion only ≈ $13,091/yr straight-line illustration. 3) At sale: residence portion -> Strategy 5 exclusion; rental portion -> recapture + gain unless 1031'd. 4) Brandy's REPS hours (Strategy 2) can make the rental losses from this building usable — log hours per unit. 5) Personal-portion mortgage interest/taxes follow normal home rules; rental portion follows rental rules. Two ledgers from day one. | D13: $600k 4-plex sold at $800k after 5 years: ~$40k residence gain excluded; ~$65k recapture + ~$120k gain on rental side (illustration — your strategist runs your real allocation). | E13: YES — set the allocation % at closing and keep two expense buckets | F13: Closing statement, allocation worksheet, per-unit logs (hours, mileage, expenses), listing/lease proof for the rental units. | G13: One blended ledger (personal + rental mixed) — it quietly poisons depreciation, the exclusion math, and the audit trail at the same time.
A14: Sources & currency note: Hour tests IRS Pub. 925 / Sec. 469(c)(7); STR 7-day rule Temp. Reg. 1.469-1T; mileage Notice 2026-10 (2026: 72.5c) / Notice 2025-05 (2025: 70c); home office Pub. 587 ($5/sq ft simplified, 300 sq ft cap); Augusta Sec. 280A(g); kids FICA Sec. 3121(b)(3) & FUTA Sec. 3306; 1031 Sec. 1031 + Form 8824; home exclusion Sec. 121. Bonus-depreciation restoration: 2025 Act (property acquired/placed after Jan 19, 2025, at 100%) — verify the rate for your year with your strategist. Figures marked 'illustration' are examples, not guarantees.

Sheet YEAR-END PACKET
A1: YEAR-END PACKET — hand this file + this checklist to your tax strategist
A2: Totals below flow in from your logs. Your job: gather the paperwork, tick the boxes, and have the planning conversation BEFORE December 31 — elections and grouping cannot be retrofitted in April.
B4: Year at a glance (automatic) | D4: Total
B5: Tax year | D5: ='SETUP & INPUTS'!B5 -> 2026
B6: Brandy 'Counts' hours (REPS progress vs 750) | D6: ='HOURS TESTS'!B5 -> 5.5
B7: REPS grade | D7: ='HOURS TESTS'!B9 -> NOT YET
B8: Business miles | D8: ='MILEAGE SUMMARY'!B5 -> 40.5
B9: Standard mileage deduction | D9: ='MILEAGE SUMMARY'!B10 -> 29.3625
B10: Better home-office deduction (compare — strategist elects) | D10: =MAX('HOME OFFICE & VEHICLE'!B8,'HOME OFFICE & VEHICLE'!B20) -> 750
B11: Better vehicle deduction (compare — method rules control) | D11: ='HOME OFFICE & VEHICLE'!B37 -> 29.3625
B12: Kids' wages deducted | D12: ='KIDS & AUGUSTA'!F12 -> 1800
B13: Augusta tax-free rent (days x rate) | D13: ='KIDS & AUGUSTA'!B22 -> 0
B15: HAND-OFF CHECKLIST
A16: Done? | B16: Document / decision | D16: Status | E16: Notes
B17: This workbook (Hours Log + Mileage Log complete through Dec 31)
B18: Jan 1 and Dec 31 odometer photos for every vehicle
B19: MileIQ annual report (classified) exported and filed
B20: Brandy's outside-job hours proof (pay stubs / employer letter) for the >50% test
B21: REPS grouping election decision — made with the strategist, statement prepared for the return
B22: Cost-segregation study report(s) + placed-in-service proof for any new property
B23: Per-property P&L / ledger export (FORGE Rental Manager) for every property
B24: Closing statements for anything bought or sold; QI paperwork + Form 8824 draft for any 1031
B25: Home-office worksheet (this file) + home expense receipts; office sq-ft sketch/photo
B26: Kids: timesheets, job descriptions, payroll register, W-2s, Roth IRA statements
B27: Augusta: rental agreement, market-rent comps, minutes, invoices, proof of payment (<=14 days)
B28: House-hack: allocation worksheet (personal vs rental %) and per-unit expense buckets
... B30: Questions list for the strategist (elections to make, entity changes, next year's purchases timed for placed-in-service)
